Metadata-Version: 2.3
Name: customer_purchases
Version: 1.0.0
Summary: Customer purchases large dataset
License: MIT License Copyright (c)
Author: Slimane Rhaytou
Requires-Python: >=3.12
Classifier: License :: Other/Proprietary License
Classifier: Programming Language :: Python :: 3
Classifier: Programming Language :: Python :: 3.12
Classifier: Programming Language :: Python :: 3.13
Requires-Dist: numpy (>=2.3.2,<3.0.0)
Requires-Dist: pandas (>=2.3.1,<3.0.0)
Requires-Dist: python-dotenv (>=1.1.1,<2.0.0)
